sitemap_harvester/__init__.py
sitemap_harvester/cli.py
sitemap_harvester/sitemap_harvester.py
sitemap_harvester-1.0.4.dist-info/licenses/LICENSE
sitemap_harvester-1.0.4.dist-info/METADATA
sitemap_harvester-1.0.4.dist-info/WHEEL
sitemap_harvester-1.0.4.dist-info/entry_points.txt
sitemap_harvester-1.0.4.dist-info/top_level.txt
sitemap_harvester-1.0.4.dist-info/RECORD
