Metadata-Version: 2.4
Name: sitemap-harvester
Version: 1.0.4
Summary: A tool to crawl website sitemaps and create a CSV report of URLs and their metadata
Author-email: Meysam Azad <meysam@developer-friendly.blog>
Project-URL: Homepage, https://github.com/meysam81/sitemap-harvester
Classifier: Intended Audience :: Developers
Classifier: License :: OSI Approved :: MIT License
Classifier: Operating System :: OS Independent
Classifier: Programming Language :: Python :: 3
Classifier: Programming Language :: Python :: 3.7
Classifier: Programming Language :: Python :: 3.8
Classifier: Programming Language :: Python :: 3.9
Classifier: Programming Language :: Python :: 3.10
Classifier: Programming Language :: Python :: 3.11
Classifier: Programming Language :: Python :: 3.12
Classifier: Programming Language :: Python :: 3.13
Classifier: Programming Language :: Python :: 3.14
Requires-Python: <4.0,>=3.7
License-File: LICENSE
Requires-Dist: requests<3,>=2
Requires-Dist: beautifulsoup4<4.15
Dynamic: license-file
